{
  "url": "https://crawlee.dev/docs/3.5/deployment",
  "unique_key": "https://crawlee.dev/docs/3.5/deployment",
  "method": "GET",
  "payload": null,
  "headers": {},
  "user_data": {},
  "retry_count": 0,
  "no_retry": false,
  "loaded_url": null,
  "handled_at": null,
  "id": "Rh9hUAGco3sKQKS",
  "json_": "{\n  \"url\": \"https://crawlee.dev/docs/3.5/deployment\",\n  \"unique_key\": \"https://crawlee.dev/docs/3.5/deployment\",\n  \"method\": \"GET\",\n  \"payload\": null,\n  \"headers\": {},\n  \"user_data\": {},\n  \"retry_count\": 0,\n  \"no_retry\": false,\n  \"loaded_url\": null,\n  \"handled_at\": null,\n  \"id\": \"Rh9hUAGco3sKQKS\",\n  \"json_\": null,\n  \"order_no\": null\n}",
  "order_no": "1722931251506.057024"
}